editor/__init__.py
python_editor_hotoffthehamster-1.1.1.dist-info/LICENSE
python_editor_hotoffthehamster-1.1.1.dist-info/METADATA
python_editor_hotoffthehamster-1.1.1.dist-info/WHEEL
python_editor_hotoffthehamster-1.1.1.dist-info/RECORD
